exobengal/__init__.py
exobengal/exobengal.py
exobengal-1.1.2.dist-info/licenses/LICENSE
exobengal-1.1.2.dist-info/METADATA
exobengal-1.1.2.dist-info/WHEEL
exobengal-1.1.2.dist-info/top_level.txt
exobengal-1.1.2.dist-info/RECORD
