Metadata-Version: 2.4
Name: exobengal
Version: 1.1.2
Summary: A python package to train Machine Learning models on Kepler Datasets with customizable hyperparameters to detect exoplanet
License-File: LICENSE
Requires-Dist: numpy
Requires-Dist: matplotlib
Requires-Dist: pandas
Requires-Dist: seaborn
Requires-Dist: scikit-learn
Requires-Dist: joblib
Requires-Dist: tensorflow
Dynamic: license-file
